{
	"info": {
		"_postman_id": "8cda32f0-6fd2-4cd6-9f4a-5dbb56ff4a63",
		"name": "Teste People-Crm",
		"schema": "https://schema.getpostman.com/json/collection/v2.1.0/collection.json",
		"_exporter_id": "24924169"
	},
	"item": [
		{
			"name": "Person",
			"item": [
				{
					"name": "get all people",
					"request": {
						"method": "GET",
						"header": [],
						"url": {
							"raw": "localhost:8080/person",
							"host": [
								"localhost"
							],
							"port": "8080",
							"path": [
								"person"
							]
						}
					},
					"response": []
				},
				{
					"name": "get person by id",
					"request": {
						"method": "GET",
						"header": [],
						"url": {
							"raw": "localhost:8080/person",
							"host": [
								"localhost"
							],
							"port": "8080",
							"path": [
								"person"
							]
						}
					},
					"response": []
				},
				{
					"name": "post add person",
					"request": {
						"method": "POST",
						"header": [],
						"body": {
							"mode": "raw",
							"raw": "{\n    \"birthday\": \"2023-01-01\",\n    \"name\": \"João\"\n}",
							"options": {
								"raw": {
									"language": "json"
								}
							}
						},
						"url": {
							"raw": "localhost:8080/person",
							"host": [
								"localhost"
							],
							"port": "8080",
							"path": [
								"person"
							]
						}
					},
					"response": []
				},
				{
					"name": "delete person",
					"request": {
						"method": "DELETE",
						"header": [],
						"url": {
							"raw": "localhost:8080/person",
							"host": [
								"localhost"
							],
							"port": "8080",
							"path": [
								"person"
							]
						}
					},
					"response": []
				},
				{
					"name": "put update person",
					"request": {
						"method": "PUT",
						"header": [],
						"body": {
							"mode": "raw",
							"raw": "{\n    \"birthday\": \"2023-01-01\",\n    \"mainAddress\": null,\n    \"name\": \"Mendes\"\n}",
							"options": {
								"raw": {
									"language": "json"
								}
							}
						},
						"url": {
							"raw": "localhost:8080/person/1",
							"host": [
								"localhost"
							],
							"port": "8080",
							"path": [
								"person",
								"1"
							]
						}
					},
					"response": []
				},
				{
					"name": "get all addresses of person by ID",
					"request": {
						"method": "GET",
						"header": [],
						"url": {
							"raw": "localhost:8080/person/1/address",
							"host": [
								"localhost"
							],
							"port": "8080",
							"path": [
								"person",
								"1",
								"address"
							]
						}
					},
					"response": []
				},
				{
					"name": "put add main address to person",
					"request": {
						"method": "PUT",
						"header": [],
						"body": {
							"mode": "raw",
							"raw": "",
							"options": {
								"raw": {
									"language": "json"
								}
							}
						},
						"url": {
							"raw": "localhost:8080/person/1/mainaddress/1",
							"host": [
								"localhost"
							],
							"port": "8080",
							"path": [
								"person",
								"1",
								"mainaddress",
								"1"
							]
						}
					},
					"response": []
				},
				{
					"name": "put add address to person",
					"request": {
						"method": "PUT",
						"header": [],
						"body": {
							"mode": "raw",
							"raw": "",
							"options": {
								"raw": {
									"language": "json"
								}
							}
						},
						"url": {
							"raw": "localhost:8080/person/1/addaddress/1",
							"host": [
								"localhost"
							],
							"port": "8080",
							"path": [
								"person",
								"1",
								"addaddress",
								"1"
							]
						}
					},
					"response": []
				}
			]
		},
		{
			"name": "Address",
			"item": [
				{
					"name": "post add address",
					"request": {
						"method": "POST",
						"header": [],
						"body": {
							"mode": "raw",
							"raw": "{\n    \"number\": 123,\n    \"publicPlace\": \"Flores\",\n    \"cep\": \"cep\"\n}",
							"options": {
								"raw": {
									"language": "json"
								}
							}
						},
						"url": {
							"raw": "localhost:8080/address",
							"host": [
								"localhost"
							],
							"port": "8080",
							"path": [
								"address"
							]
						}
					},
					"response": []
				},
				{
					"name": "get all address",
					"request": {
						"method": "GET",
						"header": [],
						"url": {
							"raw": "localhost:8080/address",
							"host": [
								"localhost"
							],
							"port": "8080",
							"path": [
								"address"
							]
						}
					},
					"response": []
				},
				{
					"name": "get address by id",
					"request": {
						"method": "GET",
						"header": [],
						"url": {
							"raw": "localhost:8080/address/1",
							"host": [
								"localhost"
							],
							"port": "8080",
							"path": [
								"address",
								"1"
							]
						}
					},
					"response": []
				},
				{
					"name": "put address",
					"request": {
						"method": "PUT",
						"header": [],
						"body": {
							"mode": "raw",
							"raw": "{\n    \"number\": 123,\n    \"publicPlace\": \"Umari\",\n    \"cep\": \"cep\"\n}",
							"options": {
								"raw": {
									"language": "json"
								}
							}
						},
						"url": {
							"raw": "localhost:8080/address/1",
							"host": [
								"localhost"
							],
							"port": "8080",
							"path": [
								"address",
								"1"
							]
						}
					},
					"response": []
				},
				{
					"name": "delete address",
					"request": {
						"method": "DELETE",
						"header": [],
						"url": {
							"raw": "localhost:8080/address/1",
							"host": [
								"localhost"
							],
							"port": "8080",
							"path": [
								"address",
								"1"
							]
						}
					},
					"response": []
				}
			]
		},
		{
			"name": "Fill Database",
			"item": [
				{
					"name": "Fill database",
					"request": {
						"method": "GET",
						"header": [],
						"url": {
							"raw": "localhost:8080/fillDatabase",
							"host": [
								"localhost"
							],
							"port": "8080",
							"path": [
								"fillDatabase"
							]
						}
					},
					"response": []
				}
			]
		}
	]
}